quicksocket-1.0.0.dist-info/METADATA
quicksocket-1.0.0.dist-info/WHEEL
quicksocket/server.py
quicksocket/__init__.py
quicksocket/quicksocket.cp38-win_amd64.pyd
quicksocket-1.0.0.dist-info/RECORD
