Metadata-Version: 2.1
Name: quicksocket
Version: 1.0.0
Summary: A simple, natively parallel WebSocket server module for Python built with
Keywords: python,websocket
Home-Page: https://github.com/nickjbenson/quicksocket
Author: Nick Benson <nickjbenson@gmail.com>
Author-email: Nick Benson <nickjbenson@gmail.com>
License: MIT
Project-URL: Source Code, https://github.com/nickjbenson/quicksocket
